poetry_exec_plugin/plugin.py
poetry_exec_plugin-1.0.1.dist-info/LICENSE
poetry_exec_plugin-1.0.1.dist-info/METADATA
poetry_exec_plugin-1.0.1.dist-info/WHEEL
poetry_exec_plugin-1.0.1.dist-info/entry_points.txt
poetry_exec_plugin-1.0.1.dist-info/RECORD
