Metadata-Version: 2.3
Name: poetry-exec-plugin
Version: 1.0.1
Summary: A plugin for poetry that allows you to execute scripts defined in your pyproject.toml, just like you can in npm or pipenv.
License: MIT
Author: keattang
Requires-Python: >=3.9,<4.0
Classifier: License :: OSI Approved :: MIT License
Classifier: Programming Language :: Python :: 3
Classifier: Programming Language :: Python :: 3.9
Classifier: Programming Language :: Python :: 3.10
Classifier: Programming Language :: Python :: 3.11
Classifier: Programming Language :: Python :: 3.12
Classifier: Programming Language :: Python :: 3.13
Requires-Dist: pip (>=25.0.1,<26.0.0)
Requires-Dist: poetry (>=1.2.0,<3.0.0)
Requires-Dist: toml (>=0.10.2,<0.11.0)
Project-URL: Homepage, https://github.com/keattang/poetry-exec-plugin
Project-URL: Repository, https://github.com/keattang/poetry-exec-plugin
